README.rst
setup.cfg
setup.py
tsuru/__init__.py
tsuru/client.py
tsuru/exceptions.py
tsuru.egg-info/PKG-INFO
tsuru.egg-info/SOURCES.txt
tsuru.egg-info/dependency_links.txt
tsuru.egg-info/not-zip-safe
tsuru.egg-info/requires.txt
tsuru.egg-info/top_level.txt
tsuru/models/__init__.py
tsuru/models/app.py
tsuru/models/base.py
tsuru/models/deploy.py
tsuru/models/env.py
tsuru/models/lock.py
tsuru/models/log.py
tsuru/models/plan.py
tsuru/models/platform.py
tsuru/models/team.py
tsuru/models/unit.py