Metadata-Version: 1.1
Name: tsuru
Version: 0.1.0
Summary: Tsuru API client for Python
Home-page: UNKNOWN
Author: eduK
Author-email: pd@eduk.com.br
License: MIT
Platform: UNKNOWN
Classifier: Development Status :: 5 - Production/Stable
Classifier: Intended Audience :: Developers
Classifier: License :: OSI Approved :: MIT License
Classifier: Programming Language :: Python :: 3
Classifier: Programming Language :: Python :: 3.6
Classifier: Programming Language :: Python :: 3.7
Classifier: Programming Language :: Python
Classifier: Topic :: Internet :: WWW/HTTP
Classifier: Topic :: Software Development :: Testing
